zinq/__init__.py
zinq/launch.py
zinq/bin/zinq-aarch64-freebsd
zinq/bin/zinq-aarch64-linux
zinq/bin/zinq-aarch64-macos
zinq/bin/zinq-aarch64-netbsd
zinq/bin/zinq-aarch64-windows.exe
zinq/bin/zinq-arm-linux
zinq/bin/zinq-riscv32-linux
zinq/bin/zinq-riscv64-linux
zinq/bin/zinq-x86-linux
zinq/bin/zinq-x86_64-freebsd
zinq/bin/zinq-x86_64-linux
zinq/bin/zinq-x86_64-macos
zinq/bin/zinq-x86_64-netbsd
zinq/bin/zinq-x86_64-windows.exe
zinq-0.5.4.dist-info/licenses/LICENSE
zinq-0.5.4.dist-info/METADATA
zinq-0.5.4.dist-info/WHEEL
zinq-0.5.4.dist-info/entry_points.txt
zinq-0.5.4.dist-info/top_level.txt
zinq-0.5.4.dist-info/RECORD
