Metadata-Version: 2.4
Name: zinq
Version: 0.5.4
Summary: Implementations of electronic structure methods and mathematical algorithms in Zig, focusing on clarity, simplicity, and modern system programming.
Author-email: tjira <tom.jira@gmail.com>
Project-URL: Homepage, https://tjira.github.io/zinq/
Project-URL: Bug Tracker, https://github.com/tjira/zinq/issues
License-File: LICENSE
Dynamic: license-file
